sequor/__init__.py
sequor/_version.py
sequor/cli.py
sequor/common/__init__.py
sequor/common/common.py
sequor/common/data_loader.py
sequor/common/executor_utils.py
sequor/common/telemetry.py
sequor/core/__init__.py
sequor/core/context.py
sequor/core/environment.py
sequor/core/execution_stack_entry.py
sequor/core/flow.py
sequor/core/flow_log_entry.py
sequor/core/instance.py
sequor/core/job.py
sequor/core/op.py
sequor/core/registry.py
sequor/core/user_error.py
sequor/core/variable_bindings.py
sequor/operations/__init__.py
sequor/operations/block.py
sequor/operations/execute.py
sequor/operations/for_each.py
sequor/operations/http_request.py
sequor/operations/if_op.py
sequor/operations/migrate_schema.py
sequor/operations/print.py
sequor/operations/run_flow.py
sequor/operations/set_variable.py
sequor/operations/transform.py
sequor/project/__init__.py
sequor/project/project.py
sequor/project/specification.py
sequor/source/__init__.py
sequor/source/column.py
sequor/source/column_schema.py
sequor/source/connection.py
sequor/source/data_type.py
sequor/source/model.py
sequor/source/row.py
sequor/source/source.py
sequor/source/table_address.py
sequor/source/sources/duckdb_connection.py
sequor/source/sources/duckdb_source.py
sequor/source/sources/http_source.py
sequor/source/sources/sql_connection.py
sequor/source/sources/sql_source.py
sequor-1.2.0.dist-info/licenses/LICENSE
sequor-1.2.0.dist-info/METADATA
sequor-1.2.0.dist-info/WHEEL
sequor-1.2.0.dist-info/entry_points.txt
sequor-1.2.0.dist-info/top_level.txt
sequor-1.2.0.dist-info/RECORD
