Metadata-Version: 2.4
Name: sequor
Version: 1.2.0
Summary: SQL-centric API integration platform
License: Apache-2.0
Project-URL: Homepage, https://sequor.dev/
Project-URL: GitHub, https://github.com/paloaltodatabases/sequor
Project-URL: Documentation, https://docs.sequor.dev/
Project-URL: Examples, https://github.com/paloaltodatabases/sequor-integrations
Project-URL: Newsletter, https://buttondown.com/sequor
Classifier: Programming Language :: Python :: 3
Classifier: License :: OSI Approved :: Apache Software License
Classifier: Operating System :: OS Independent
Requires-Python: >=3.9
License-File: LICENSE
Requires-Dist: pyyaml>=6.0.2
Requires-Dist: jinja2>=3.1.6
Requires-Dist: ruamel.yaml>=0.18.10
Requires-Dist: sqlalchemy>=2.0.40
Requires-Dist: typer>=0.15.2
Requires-Dist: requests>=2.32.3
Requires-Dist: requests-toolbelt>=1.0.0
Requires-Dist: authlib>=1.5.2
Requires-Dist: psycopg2-binary<2.9.10,>=2.9.0
Requires-Dist: duckdb-engine>=0.17.0
Requires-Dist: posthog>=4.0.0
Provides-Extra: dev
Requires-Dist: pytest>=7.3.1; extra == "dev"
Requires-Dist: pytest-cov>=4.1.0; extra == "dev"
Requires-Dist: responses>=0.23.1; extra == "dev"
Requires-Dist: black>=23.3.0; extra == "dev"
Requires-Dist: build>=0.10.0; extra == "dev"
Requires-Dist: twine>=4.0.2; extra == "dev"
Dynamic: license-file
